{
    "openapi": "3.0.0",
    "info": {
        "title": "Crafted By API",
        "description": "All the routes for the Crafted By shop.",
        "contact": {
            "name": "Crafted By Team",
            "email": "maxime@dysign.fr"
        },
        "version": "1.0.0"
    },
    "servers": [
        {
            "url": "http://0.0.0.0/api",
            "description": "API Server"
        }
    ],
    "paths": {
        "/product": {
            "get": {
                "tags": [
                    "Products"
                ],
                "summary": "Returns the list of all products",
                "description": "renvoie la liste des produits",
                "operationId": "22905e1f44768d097e237b248ae28fdc",
                "responses": {
                    "200": {
                        "description": "All gud my friend"
                    },
                    "400": {
                        "description": "Not gud my friend"
                    }
                }
            }
        }
    }
}